mommyplugs/__init__.py
mommyplugs-0.1.0.dist-info/LICENSE
mommyplugs-0.1.0.dist-info/METADATA
mommyplugs-0.1.0.dist-info/WHEEL
mommyplugs-0.1.0.dist-info/top_level.txt
mommyplugs-0.1.0.dist-info/RECORD
