Metadata-Version: 2.1
Name: mommyplugs
Version: 0.1.0
Summary: A collection of handy utility plugins
Home-page: https://github.com/yourgithub/mommyplugs
Author: Your Name
Author-email: your.email@example.com
License: MIT
Keywords: progress bar utility
Classifier: Development Status :: 3 - Alpha
Classifier: Intended Audience :: Developers
Classifier: License :: OSI Approved :: MIT License
Classifier: Programming Language :: Python :: 3
Classifier: Programming Language :: Python :: 3.7
Classifier: Programming Language :: Python :: 3.8
Classifier: Programming Language :: Python :: 3.9
License-File: LICENSE
